waves/README.rst
waves/__init__.py
waves/_build.py
waves/_docs.py
waves/_fetch.py
waves/_main.py
waves/_parameter_study.py
waves/_print_study.py
waves/_qoi.py
waves/_settings.py
waves/_utilities.py
waves/_version.py
waves/_visualize.py
waves/conftest.py
waves/exceptions.py
waves/parameter_generators.py
waves/pyproject.toml
waves/qoi.py
waves/scons_extensions.py
waves/_abaqus/__init__.py
waves/_abaqus/_settings.py
waves/_abaqus/abaqus_file_parser.py
waves/_abaqus/odb_extract.py
waves/_tests/__init__.py
waves/_tests/common.py
waves/_tests/simulation_1_expected_qois.csv
waves/_tests/test_abaqus_file_parser.py
waves/_tests/test_build.py
waves/_tests/test_cartesian_product.py
waves/_tests/test_common.py
waves/_tests/test_custom_study.py
waves/_tests/test_docs.py
waves/_tests/test_fetch.py
waves/_tests/test_help_messages.py
waves/_tests/test_io.py
waves/_tests/test_latin_hypercube.py
waves/_tests/test_main.py
waves/_tests/test_odb_extract.py
waves/_tests/test_one_at_a_time.py
waves/_tests/test_parameter_generators.py
waves/_tests/test_parameter_study.py
waves/_tests/test_print_study.py
waves/_tests/test_qoi.py
waves/_tests/test_salib_sampler.py
waves/_tests/test_scipy_sampler.py
waves/_tests/test_scons_extensions.py
waves/_tests/test_sobol_sequence.py
waves/_tests/test_system.py
waves/_tests/test_utilities.py
waves/_tests/test_visualize.py
waves/docs/abstract.html
waves/docs/api.html
waves/docs/changelog.html
waves/docs/citation.html
waves/docs/cli.html
waves/docs/computational_practices_archival.html
waves/docs/computational_practices_build_system.html
waves/docs/computational_practices_compute_environment.html
waves/docs/computational_practices_documentation.html
waves/docs/computational_practices_introduction.html
waves/docs/computational_practices_regression_testing.html
waves/docs/computational_practices_version_control.html
waves/docs/devops.html
waves/docs/genindex.html
waves/docs/glossary.html
waves/docs/index.html
waves/docs/installation.html
waves_workflows-1.0.1.dist-info/licenses/LICENSE.txt
waves_workflows-1.0.1.dist-info/METADATA
waves_workflows-1.0.1.dist-info/WHEEL
waves_workflows-1.0.1.dist-info/entry_points.txt
waves_workflows-1.0.1.dist-info/top_level.txt
waves_workflows-1.0.1.dist-info/RECORD
