Metadata-Version: 2.4
Name: waves-workflows
Version: 1.0.1
Summary: Computational science and engineering parameteric study workflows
Author-email: Kyle Brindley <kbrindley@lanl.gov>, Prabhu Khalsa <pkhalsa@lanl.gov>, Thomas Roberts <tproberts@lanl.gov>, Sergio Cordova <sergioc@lanl.gov>, Matthew Fister <mwfister@lanl.gov>, Chris Johnson <clj@lanl.gov>, Scott Ouellette <souellette@lanl.gov>
License-Expression: BSD-3-Clause
Project-URL: homepage, https://github.com/lanl-aea/waves
Project-URL: documentation, https://github.com/lanl-aea/waves
Project-URL: repository, https://github.com/lanl-aea/waves
Project-URL: changelog, https://lanl-aea.github.io/waves/changelog.html
Classifier: Development Status :: 4 - Beta
Classifier: Environment :: Console
Classifier: Intended Audience :: Science/Research
Classifier: Operating System :: OS Independent
Classifier: Programming Language :: Python :: 3
Classifier: Topic :: Scientific/Engineering
Requires-Python: >=3.10
License-File: LICENSE.txt
Requires-Dist: h5netcdf
Requires-Dist: h5py
Requires-Dist: matplotlib
Requires-Dist: networkx
Requires-Dist: numpy
Requires-Dist: pyyaml
Requires-Dist: salib>=1.4.6
Requires-Dist: scipy>=1.7
Requires-Dist: scons>=4
Requires-Dist: xarray>=2024.10.0
Dynamic: license-file
